{"id": 2479, "annotations": [{"id": 1534, "completed_by": 5, "result": [{"original_width": 1920, "original_height": 1080, "image_rotation": 0, "value": {"x": 67.80451308779257, "y": 58.5881363334423, "width": 10.838784409940729, "height": 11.526003010488678, "rotation": 0, "rectanglelabels": ["\u5bfe\u5411\u8eca"]}, "id": "g_qrLVksKy", "from_name": "label", "to_name": "image", "type": "rectanglelabels", "origin": "manual"}, {"original_width": 1920, "original_height": 1080, "image_rotation": 0, "value": {"x": 54.300316814895034, "y": 62.05739382009617, "width": 2.0449897635310275, "height": 1.7044208722593608, "rotation": 0, "rectanglelabels": ["\u5bfe\u5411\u8eca"]}, "id": "z7yRDoytyW", "from_name": "label", "to_name": "image", "type": "rectanglelabels", "origin": "manual"}, {"original_width": 1920, "original_height": 1080, "image_rotation": 0, "value": {"x": 45.66037736181862, "y": 62.043228299396404, "width": 1.5327228765253533, "height": 2.0866703205477553, "rotation": 0, "rectanglelabels": ["\u524d\u65b9\u8eca"]}, "id": "uATt7Iu69O", "from_name": "label", "to_name": "image", "type": "rectanglelabels", "origin": "manual"}, {"original_width": 1920, "original_height": 1080, "image_rotation": 0, "value": {"x": 46.87172286100801, "y": 61.208560171177325, "width": 1.0877388155986365, "height": 2.2184600250034, "rotation": 0, "rectanglelabels": ["\u524d\u65b9\u8eca"]}, "id": "FLMzX-ZXfH", "from_name": "label", "to_name": "image", "type": "rectanglelabels", "origin": "manual"}, {"original_width": 1920, "original_height": 1080, "image_rotation": 0, "value": {"x": 44.251261168884014, "y": 61.31838492489035, "width": 0.7292794331854513, "height": 1.5375465519825597, "rotation": 0, "rectanglelabels": ["\u524d\u65b9\u8eca"]}, "id": "kAeHkYC0te", "from_name": "label", "to_name": "image", "type": "rectanglelabels", "origin": "manual"}, {"original_width": 1920, "original_height": 1080, "image_rotation": 0, "value": {"x": 45.21876500254285, "y": 60.755845356643505, "width": 0.9214316413129007, "height": 1.9169411557185134, "rotation": 0, "rectanglelabels": ["\u524d\u65b9\u8eca"]}, "id": "McYKL3HI17", "from_name": "label", "to_name": "image", "type": "rectanglelabels", "origin": "manual"}], "was_cancelled": false, "ground_truth": false, "created_at": "2023-02-22T06:01:56.408699Z", "updated_at": "2023-02-22T06:01:56.408742Z", "lead_time": 47.246, "prediction": {}, "result_count": 0, "task": 2479, "project": 14, "parent_prediction": null, "parent_annotation": null}], "file_upload": "c05bd66a-inouesan-task2.json", "drafts": [], "predictions": [], "data": {"image": "s3://mayo-annotation-images/fujimic-niigata/videos/\u9ad8\u901fETC\u30b1\u3099\u30fc\u30c8_\u5408\u6d41/500625.png"}, "meta": {}, "created_at": "2023-02-16T12:16:32.154790Z", "updated_at": "2023-02-22T06:01:56.599293Z", "inner_id": 479, "total_annotations": 1, "cancelled_annotations": 0, "total_predictions": 0, "comment_count": 0, "unresolved_comment_count": 0, "last_comment_updated_at": null, "project": 14, "updated_by": 5, "comment_authors": []}