{"id": 1179, "annotations": [{"id": 2117, "completed_by": 8, "result": [{"original_width": 1920, "original_height": 1080, "image_rotation": 0, "value": {"x": 43.1960049937578, "y": 58.31485587583147, "width": 18.352059925093638, "height": 26.829268292682936, "rotation": 0, "rectanglelabels": ["\u524d\u65b9\u8eca"]}, "id": "7lWTcq8V9J", "from_name": "label", "to_name": "image", "type": "rectanglelabels", "origin": "manual"}, {"original_width": 1920, "original_height": 1080, "image_rotation": 0, "value": {"x": 19.850187265917615, "y": 55.875831485587526, "width": 21.47315855181026, "height": 25.94235033259421, "rotation": 0, "rectanglelabels": ["\u524d\u65b9\u8eca"]}, "id": "z7QecHpiFX", "from_name": "label", "to_name": "image", "type": "rectanglelabels", "origin": "manual"}, {"original_width": 1920, "original_height": 1080, "image_rotation": 0, "value": {"x": 7.990012484394504, "y": 60.75388026607541, "width": 12.858926342072413, "height": 15.077605321507736, "rotation": 0, "rectanglelabels": ["\u524d\u65b9\u8eca"]}, "id": "cEm-mRkJki", "from_name": "label", "to_name": "image", "type": "rectanglelabels", "origin": "manual"}, {"original_width": 1920, "original_height": 1080, "image_rotation": 0, "value": {"x": 75.86856331231999, "y": 55.376269992341456, "width": 10.57349169354163, "height": 8.177988157364329, "rotation": 0, "rectanglelabels": ["\u5bfe\u5411\u8eca"]}, "id": "ITCzJ3N2Q5", "from_name": "label", "to_name": "image", "type": "rectanglelabels", "origin": "manual"}, {"original_width": 1920, "original_height": 1080, "image_rotation": 0, "value": {"x": 58.21765379164984, "y": 60.373929421841936, "width": 4.860395375257057, "height": 4.8462152043641415, "rotation": 0, "rectanglelabels": ["\u5bfe\u5411\u8eca"]}, "id": "3OBL0eGnb6", "from_name": "label", "to_name": "image", "type": "rectanglelabels", "origin": "manual"}, {"original_width": 1920, "original_height": 1080, "image_rotation": 0, "value": {"x": 42.10160596842912, "y": 60.37392942184198, "width": 3.5813439607157243, "height": 4.391882528955005, "rotation": 0, "rectanglelabels": ["\u5bfe\u5411\u8eca"]}, "id": "P6aDykZgRY", "from_name": "label", "to_name": "image", "type": "rectanglelabels", "origin": "manual"}, {"original_width": 1920, "original_height": 1080, "image_rotation": 0, "value": {"x": 62.69257196373661, "y": 38.86884945247613, "width": 3.0288501265557057, "height": 1.968774926772934, "rotation": 0, "rectanglelabels": ["\u81ea\u52d5\u8eca\u4fe1\u53f7"]}, "id": "poIz7squ1v", "from_name": "label", "to_name": "image", "type": "rectanglelabels", "origin": "manual"}, {"original_width": 1920, "original_height": 1080, "image_rotation": 0, "value": {"x": 50.96969577591568, "y": 54.46760464152318, "width": 0.9379710373303077, "height": 0.45433267540913475, "rotation": 0, "rectanglelabels": ["\u81ea\u52d5\u8eca\u4fe1\u53f7"]}, "id": "h1oohqnoIG", "from_name": "label", "to_name": "image", "type": "rectanglelabels", "origin": "manual"}, {"original_width": 1920, "original_height": 1080, "image_rotation": 0, "value": {"x": 43.13839678071209, "y": 54.32861957690704, "width": 0.7687762070871994, "height": 0.7964760149922262, "rotation": 0, "rectanglelabels": ["\u81ea\u52d5\u8eca\u4fe1\u53f7"]}, "id": "jWOUjIlb4X", "from_name": "label", "to_name": "image", "type": "rectanglelabels", "origin": "manual"}, {"original_width": 1920, "original_height": 1080, "image_rotation": 0, "value": {"x": 24.095169484322906, "y": 50.70465370869242, "width": 0.4932980662142873, "height": 3.1290129160408955, "rotation": 0, "rectanglelabels": ["\u6b69\u884c\u8005\u4fe1\u53f7"]}, "id": "U4rQ9D_kEV", "from_name": "label", "to_name": "image", "type": "rectanglelabels", "origin": "manual"}, {"original_width": 1920, "original_height": 1080, "image_rotation": 0, "value": {"x": 19.16218882218004, "y": 58.965247807040384, "width": 3.3826153111836823, "height": 3.2541734326825225, "rotation": 0, "rectanglelabels": ["\u5bfe\u5411\u8eca"]}, "id": "HtFCMH-qVd", "from_name": "label", "to_name": "image", "type": "rectanglelabels", "origin": "manual"}, {"original_width": 1920, "original_height": 1080, "image_rotation": 0, "value": {"x": 39.886672211040725, "y": 66.09939725561355, "width": 25.510557138510183, "height": 3.6296549826074322, "rotation": 0, "rectanglelabels": ["\u6a2a\u65ad\u6b69\u9053"]}, "id": "o7eosfgEXN", "from_name": "label", "to_name": "image", "type": "rectanglelabels", "origin": "manual"}, {"original_width": 1920, "original_height": 1080, "image_rotation": 0, "value": {"x": 20.853957346877433, "y": 46.40930369661469, "width": 0.953028355893222, "height": 1.4105242296202334, "rotation": 0, "rectanglelabels": ["\u81ea\u52d5\u8eca\u4fe1\u53f7"]}, "id": "ubl8LHIOvc", "from_name": "label", "to_name": "image", "type": "rectanglelabels", "origin": "manual"}], "was_cancelled": false, "ground_truth": false, "created_at": "2023-02-26T07:11:07.029600Z", "updated_at": "2023-02-26T07:17:06.422721Z", "lead_time": 192.83499999999998, "prediction": {}, "result_count": 0, "task": 1179, "project": 12, "parent_prediction": null, "parent_annotation": null}], "file_upload": "3e406570-yamadasan-task1.json", "drafts": [], "predictions": [], "data": {"image": "s3://mayo-annotation-images/fujimic-niigata/object/\u6a2a\u65ad\u6b69\u9053\u4fe1\u53f7\u6a5f/400485.png"}, "meta": {}, "created_at": "2023-02-14T13:29:45.768450Z", "updated_at": "2023-02-26T07:17:06.617758Z", "inner_id": 179, "total_annotations": 1, "cancelled_annotations": 0, "total_predictions": 0, "comment_count": 0, "unresolved_comment_count": 0, "last_comment_updated_at": null, "project": 12, "updated_by": 8, "comment_authors": []}